{
  "printingModel": {
    "page": {
      "width": "21cm",
      "height": "29.7cm",
      "margin": "5mm 15mm 5mm 15mm",
      "padding": "",
      "border": "2px dashed #a6a6a6",
      "position": "relative"
    },
    "model": {
      "scale": "6",
      "type": "image/jpeg",
      "quality": "2.0",
      "typeImage": "jpeg",
      "landScape": "p",
      "unite": "cm",
      "format": "a4",
      "x": "0",
      "y": "0",
      "w": "21",
      "h": "29.7",
      "autoPrint": true
    },
    "groups": [
      {
        "name": "InformationsCenterGroup",
        "style": "",
        "position": "absolute",
        "tableLayout": "fixed",
        "maxWidth": "190px",
        "maxHeight": "",
        "width": "100%",
        "height": "",
        "x": "185px",
        "y": "115px",
        "z": "1",
        "margin": "",
        "padding": "",
        "backgroundColor": "",
        "color": "",
        "DynamicBackgroundColor": "",
        "DynamicColor": "",
        "border": "",
        "display": "table",
        "borderSpacing": "0px 3px"
      },
      {
        "name": "sitesCenterGroup",
        "style": "",
        "position": "absolute",
        "tableLayout": "fixed",
        "maxWidth": "123px",
        "maxHeight": "",
        "width": "100%",
        "height": "",
        "x": "53px",
        "y": "266px",
        "z": "1",
        "margin": "",
        "padding": "",
        "backgroundColor": "",
        "color": "",
        "DynamicBackgroundColor": "",
        "DynamicColor": "",
        "border": "",
        "display": "table",
        "borderSpacing": "0px 10px"
      },
      {
        "name": "areaCenterGroup",
        "style": "",
        "position": "absolute",
        "tableLayout": "fixed",
        "maxWidth": "333px",
        "maxHeight": "50px",
        "width": "333px",
        "height": "50px",
        "x": "48px",
        "y": "433px",
        "z": "1",
        "margin": "",
        "padding": "",
        "backgroundColor": "",
        "color": "",
        "DynamicBackgroundColor": "category.categoryColor",
        "DynamicColor": "",
        "border": "",
        "display": "table",
        "borderSpacing": "5px 3px"
      },
	        {
        "name": "InformationsSignatureLeftGroup",
        "style": "",
        "position": "absolute",
        "tableLayout": "fixed",
        "maxWidth": "190px",
        "maxHeight": "",
        "width": "100%",
        "height": "",
        "x": "100px",
        "y": "955px",
        "z": "1",
        "margin": "",
        "padding": "",
        "backgroundColor": "",
        "color": "",
        "DynamicBackgroundColor": "",
        "DynamicColor": "",
        "border": "",
        "display": "table",
        "borderSpacing": "0px 3px"
      },
	        {
        "name": "InformationsSignatureRightGroup",
        "style": "",
        "position": "absolute",
        "tableLayout": "fixed",
        "maxWidth": "190px",
        "maxHeight": "",
        "width": "100%",
        "height": "",
        "x": "600px",
        "y": "955px",
        "z": "1",
        "margin": "",
        "padding": "",
        "backgroundColor": "",
        "color": "",
        "DynamicBackgroundColor": "",
        "DynamicColor": "",
        "border": "",
        "display": "table",
        "borderSpacing": "0px 3px"
      }
    ],
    "fields": [
	  {
        "name": "accreditationLastName",
        "path": "accreditationLastName",
        "type": "text",
        "format": "",
        "style": "",
        "position": "",
        "maxWidth": "190px",
        "maxHeight": "",
        "width": "190px",
        "height": "",
        "x": "",
        "y": "",
        "z": "",
        "margin": "",
        "padding": "",
        "backgroundColor": "",
        "color": "",
        "DynamicBackgroundColor": "",
        "DynamicColor": "",
        "textAlign": "left",
        "fontFamily": "arial",
        "fontStyle": "normal",
        "calculatedFontSize": true,
        "minFontSize": "10px",
        "maxFontSize": "15px",
        "fontUnite": "px",
        "fontSize": "15px",
        "fontWeight": "bold",
        "border": "",
        "display": "table-row",
        "whiteSpace": "nowrap",
        "toUpperCase": true,
        "verticalAlign": "middle",
        "groupName": "InformationsCenterGroup"
      },
	  {
        "name": "accreditationFirstName",
        "path": "accreditationFirstName",
        "type": "text",
        "format": "",
        "style": "",
        "position": "",
        "maxWidth": "190px",
        "maxHeight": "",
        "width": "190px",
        "height": "",
        "x": "",
        "y": "",
        "z": "",
        "margin": "",
        "padding": "",
        "backgroundColor": "",
        "color": "",
        "DynamicBackgroundColor": "",
        "DynamicColor": "",
        "textAlign": "left",
        "fontFamily": "arial",
        "fontStyle": "normal",
        "calculatedFontSize": true,
        "minFontSize": "10px",
        "maxFontSize": "15px",
        "fontUnite": "px",
        "fontSize": "15px",
        "fontWeight": "bold",
        "border": "",
        "display": "table-row",
        "whiteSpace": "nowrap",
        "toUpperCase": true,
        "verticalAlign": "middle",
        "groupName": "InformationsCenterGroup"
      },
      {
        "name": "fonctionAbrev",
        "path": "fonction.fonctionAbreviation",
        "type": "text",
        "format": "",
        "style": "",
        "position": "absolute",
        "maxWidth": "100px",
        "maxHeight": "",
        "width": "100px",
        "height": "",
        "x": "273px",
        "y": "376px",
        "z": "1",
        "margin": "",
        "padding": "",
        "backgroundColor": "",
        "color": "",
        "DynamicBackgroundColor": "fonction.fonctionColor",
        "DynamicColor": "",
        "textAlign": "center",
        "fontFamily": "arial",
        "fontStyle": "normal",
        "calculatedFontSize": true,
        "minFontSize": "10px",
        "maxFontSize": "15px",
        "fontUnite": "px",
        "fontSize": "15px",
        "fontWeight": "bold",
        "border": "",
        "display": "inline-block",
        "whiteSpace": "nowrap",
        "toUpperCase": true,
        "verticalAlign": ""
      },
      {
        "name": "organizName",
        "path": "organiz.organizName",
        "type": "text",
        "format": "",
        "style": "",
        "position": "",
        "maxWidth": "190px",
        "maxHeight": "",
        "width": "190px",
        "height": "",
        "x": "",
        "y": "",
        "z": "",
        "margin": "",
        "padding": "",
        "backgroundColor": "",
        "color": "",
        "DynamicBackgroundColor": "",
        "DynamicColor": "",
        "textAlign": "left",
        "fontFamily": "arial",
        "fontStyle": "normal",
        "calculatedFontSize": true,
        "minFontSize": "10px",
        "maxFontSize": "15px",
        "fontUnite": "px",
        "fontSize": "15px",
        "fontWeight": "bold",
        "border": "",
        "display": "table-row",
        "whiteSpace": "nowrap",
        "toUpperCase": true,
        "verticalAlign": "middle",
        "groupName": "InformationsCenterGroup",
        "hidden": false
      },
	  {
        "name": "categoryName",
        "path": "category.categoryName",
        "type": "text",
        "format": "",
        "style": "",
        "position": "",
        "maxWidth": "190px",
        "maxHeight": "",
        "width": "190px",
        "height": "",
        "x": "",
        "y": "",
        "z": "",
        "margin": "",
        "padding": "",
        "backgroundColor": "",
        "color": "",
        "DynamicBackgroundColor": "",
        "DynamicColor": "",
        "textAlign": "left",
        "fontFamily": "arial",
        "fontStyle": "normal",
        "calculatedFontSize": true,
        "minFontSize": "10px",
        "maxFontSize": "15px",
        "fontUnite": "px",
        "fontSize": "15px",
        "fontWeight": "bold",
        "border": "",
        "display": "table-row",
        "whiteSpace": "nowrap",
        "toUpperCase": true,
        "verticalAlign": "middle",
        "groupName": "InformationsCenterGroup",
        "hidden": false
      },
	  {
        "name": "accreditationId",
        "path": "accreditationId",
        "type": "concat",
        "format": "",
        "style": "",
        "position": "",
        "maxWidth": "190px",
        "maxHeight": "",
        "width": "190px",
        "height": "",
        "x": "",
        "y": "",
        "z": "",
        "margin": "",
        "padding": "",
        "backgroundColor": "",
        "color": "",
        "DynamicBackgroundColor": "",
        "DynamicColor": "",
        "textAlign": "left",
        "fontFamily": "arial",
        "fontStyle": "normal",
        "calculatedFontSize": true,
        "minFontSize": "10px",
        "maxFontSize": "15px",
        "fontUnite": "px",
        "fontSize": "15px",
        "fontWeight": "bold",
        "border": "",
        "display": "table-row",
        "whiteSpace": "nowrap",
        "toUpperCase": true,
        "verticalAlign": "middle",
        "groupName": "InformationsCenterGroup",
        "childFields": [
          {
            "name": "eventAbrev",
            "path": "event.eventAbreviation",
            "separator": " / "
          },
          {
            "name": "accreditationId",
            "path": "accreditationId",
            "separator": " / "
          },
          {
            "name": "accreditationPrintNumber",
            "path": "accreditationPrintNumber",
            "separator": " "
          }
        ]
      },
      {
        "name": "siteAbrev",
        "listPath": "sites",
        "path": "siteAbreviation",
        "type": "list",
        "format": "",
        "style": "",
        "position": "",
        "maxWidth": "123px",
        "maxHeight": "",
        "width": "123px",
        "height": "",
        "x": "",
        "y": "",
        "z": "",
        "margin": "",
        "padding": "",
        "backgroundColor": "",
        "color": "",
        "DynamicBackgroundColor": "siteColor",
        "DynamicColor": "",
        "textAlign": "center",
        "fontFamily": "arial",
        "fontStyle": "normal",
        "fontSize": "15px",
        "fontWeight": "bold",
        "border": "",
        "display": "table-row",
        "whiteSpace": "nowrap",
        "toUpperCase": true,
        "order": true,
        "orderBy": "siteAbreviation",
        "orderType": "asc",
        "verticalAlign": "middle",
        "condition": true,
        "conditionElement1": "sites",
        "conditionElement1Fixed": "",
        "conditionAttribute1": "count",
        "conditionTest": ">=",
        "conditionElement2": "",
        "conditionElement2Fixed": "1",
        "conditionAttribute2": "",
        "groupName": "sitesCenterGroup"
      },
      {
        "name": "areaAbrev",
        "listPath": "fonction.areas",
        "path": "areaAbreviation",
        "type": "table",
        "fixedPosition": true,
        "format": "",
        "style": "",
        "position": "",
        "maxWidth": "20px",
        "maxHeight": "20px",
        "width": "20px",
        "height": "20px",
        "x": "",
        "y": "",
        "z": "",
        "margin": "",
        "padding": "",
        "backgroundColor": "",
        "color": "",
        "DynamicBackgroundColor": "areaColor",
        "DynamicColor": "",
        "textAlign": "center",
        "fontFamily": "arial",
        "fontStyle": "normal",
        "fontSize": "15px",
        "fontWeight": "bold",
        "border": "",
        "display": "table-cell",
        "whiteSpace": "nowrap",
        "toUpperCase": true,
        "order": true,
        "orderBy": "areaAbreviation",
        "orderType": "asc",
        "verticalAlign": "middle",
        "columnNbr": "5",
        "rowNbr": "2",
        "condition": true,
        "conditionElement1": "fonction.areas",
        "conditionElement1Fixed": "",
        "conditionAttribute1": "count",
        "conditionTest": "<",
        "conditionElement2": "",
        "conditionElement2Fixed": "11",
        "conditionAttribute2": "",
        "groupName": "areaCenterGroup"
      },
	  {
        "name": "accreditationFirstNameSignatureLeft",
        "path": "accreditationFirstNameSignatureLeft",
        "type": "concat",
        "format": "",
        "style": "",
        "position": "",
        "maxWidth": "190px",
        "maxHeight": "",
        "width": "190px",
        "height": "",
        "x": "",
        "y": "",
        "z": "",
        "margin": "",
        "padding": "",
        "backgroundColor": "",
        "color": "",
        "DynamicBackgroundColor": "",
        "DynamicColor": "",
        "textAlign": "left",
        "fontFamily": "arial",
        "fontStyle": "normal",
        "calculatedFontSize": true,
        "minFontSize": "8px",
        "maxFontSize": "8px",
        "fontUnite": "px",
        "fontSize": "8px",
        "fontWeight": "bold",
        "border": "",
        "display": "table-row",
        "whiteSpace": "nowrap",
        "toUpperCase": true,
        "verticalAlign": "middle",
        "groupName": "InformationsSignatureLeftGroup",
                "childFields": [
          {
            "name": "accreditationLastName",
            "path": "accreditationLastName",
            "separator": " "
          },
		  {
            "name": "accreditationFirstName",
            "path": "accreditationFirstName",
            "separator": " "
          }
        ]
      },
	  {
        "name": "accreditationIdSignatureLeft",
        "path": "accreditationIdSignatureLeft",
        "type": "concat",
        "format": "",
        "style": "",
        "position": "",
        "maxWidth": "190px",
        "maxHeight": "",
        "width": "190px",
        "height": "",
        "x": "",
        "y": "",
        "z": "",
        "margin": "",
        "padding": "",
        "backgroundColor": "",
        "color": "",
        "DynamicBackgroundColor": "",
        "DynamicColor": "",
        "textAlign": "left",
        "fontFamily": "arial",
        "fontStyle": "normal",
        "calculatedFontSize": true,
        "minFontSize": "8px",
        "maxFontSize": "8px",
        "fontUnite": "px",
        "fontSize": "8px",
        "fontWeight": "bold",
        "border": "",
        "display": "table-row",
        "whiteSpace": "nowrap",
        "toUpperCase": true,
        "verticalAlign": "middle",
        "groupName": "InformationsSignatureLeftGroup",
        "childFields": [
          {
            "name": "eventAbrev",
            "path": "event.eventAbreviation",
            "separator": " / "
          },
          {
            "name": "accreditationId",
            "path": "accreditationId",
            "separator": " / "
          },
          {
            "name": "accreditationPrintNumber",
            "path": "accreditationPrintNumber",
            "separator": " "
          }
        ]
      },
	  {
        "name": "accreditationPrintDateSignatureLeft",
        "path": "accreditationPrintDate",
        "type": "text",
        "format": "",
        "style": "",
        "position": "",
        "maxWidth": "190px",
        "maxHeight": "",
        "width": "190px",
        "height": "",
        "x": "",
        "y": "",
        "z": "",
        "margin": "",
        "padding": "",
        "backgroundColor": "",
        "color": "",
        "DynamicBackgroundColor": "",
        "DynamicColor": "",
        "textAlign": "left",
        "fontFamily": "arial",
        "fontStyle": "normal",
        "calculatedFontSize": true,
        "minFontSize": "8px",
        "maxFontSize": "8px",
        "fontUnite": "px",
        "fontSize": "8px",
        "fontWeight": "bold",
        "border": "",
        "display": "table-row",
        "whiteSpace": "nowrap",
        "toUpperCase": true,
        "verticalAlign": "middle",
        "groupName": "InformationsSignatureLeftGroup",
        "hidden": false
      },
	  {
        "name": "accreditationFirstNameSignatureRight",
        "path": "accreditationFirstNameSignatureRight",
        "type": "concat",
        "format": "",
        "style": "",
        "position": "",
        "maxWidth": "190px",
        "maxHeight": "",
        "width": "190px",
        "height": "",
        "x": "",
        "y": "",
        "z": "",
        "margin": "",
        "padding": "",
        "backgroundColor": "",
        "color": "",
        "DynamicBackgroundColor": "",
        "DynamicColor": "",
        "textAlign": "left",
        "fontFamily": "arial",
        "fontStyle": "normal",
        "calculatedFontSize": true,
        "minFontSize": "8px",
        "maxFontSize": "8px",
        "fontUnite": "px",
        "fontSize": "8px",
        "fontWeight": "bold",
        "border": "",
        "display": "table-row",
        "whiteSpace": "nowrap",
        "toUpperCase": true,
        "verticalAlign": "middle",
        "groupName": "InformationsSignatureRightGroup",
                "childFields": [
          {
            "name": "accreditationLastName",
            "path": "accreditationLastName",
            "separator": " "
          },
		  {
            "name": "accreditationFirstName",
            "path": "accreditationFirstName",
            "separator": ""
          }
        ]
      },
	  {
        "name": "accreditationIdSignatureRight",
        "path": "accreditationIdSignatureRight",
        "type": "concat",
        "format": "",
        "style": "",
        "position": "",
        "maxWidth": "190px",
        "maxHeight": "",
        "width": "190px",
        "height": "",
        "x": "",
        "y": "",
        "z": "",
        "margin": "",
        "padding": "",
        "backgroundColor": "",
        "color": "",
        "DynamicBackgroundColor": "",
        "DynamicColor": "",
        "textAlign": "left",
        "fontFamily": "arial",
        "fontStyle": "normal",
        "calculatedFontSize": true,
        "minFontSize": "8px",
        "maxFontSize": "8px",
        "fontUnite": "px",
        "fontSize": "8px",
        "fontWeight": "bold",
        "border": "",
        "display": "table-row",
        "whiteSpace": "nowrap",
        "toUpperCase": true,
        "verticalAlign": "middle",
        "groupName": "InformationsSignatureRightGroup",
        "childFields": [
          {
            "name": "eventAbrev",
            "path": "event.eventAbreviation",
            "separator": " / "
          },
          {
            "name": "accreditationId",
            "path": "accreditationId",
            "separator": " / "
          },
          {
            "name": "accreditationPrintNumber",
            "path": "accreditationPrintNumber",
            "separator": " "
          }
        ]
      },
	  {
        "name": "accreditationPrintDateSignatureRight",
        "path": "accreditationPrintDate",
        "type": "text",
        "format": "",
        "style": "",
        "position": "",
        "maxWidth": "190px",
        "maxHeight": "",
        "width": "190px",
        "height": "",
        "x": "",
        "y": "",
        "z": "",
        "margin": "",
        "padding": "",
        "backgroundColor": "",
        "color": "",
        "DynamicBackgroundColor": "",
        "DynamicColor": "",
        "textAlign": "left",
        "fontFamily": "arial",
        "fontStyle": "normal",
        "calculatedFontSize": true,
        "minFontSize": "8px",
        "maxFontSize": "8px",
        "fontUnite": "px",
        "fontSize": "8px",
        "fontWeight": "bold",
        "border": "",
        "display": "table-row",
        "whiteSpace": "nowrap",
        "toUpperCase": true,
        "verticalAlign": "middle",
        "groupName": "InformationsSignatureRightGroup",
        "hidden": false
      }
    ],
    "images": [
      {
        "name": "accreditationPhoto",
        "path": "accreditationPhoto",
        "sourceType": "attribute",
        "contentType": "accreditationPhotoContentType",
        "format": "",
		"width": "110px",
		"height": "110px",
        "maxWidth": "",
        "maxHeight": "",
        "style": "",
        "position": "absolute",
        "x": "45px",
        "y": "125px",
        "z": "1",
        "margin": "",
        "padding": "",
        "border": "",
        "display": "inline-block",
        "verticalAlign": ""
      },
	  {
        "name": "allAreasPhoto",
        "path": "",
        "sourceType": "setting",
        "settingId": "1",
        "contentType": "",
        "format": "",
        "width": "20px",
        "height": "20px",
        "maxWidth": "20px",
        "maxHeight": "20px",
        "style": "",
        "position": "absolute",
        "x": "290px",
        "y": "31px",
        "z": "2",
        "margin": "",
        "padding": "",
        "border": "",
        "display": "inline-block",
        "verticalAlign": "",
        "condition": true,
        "conditionElement1": "fonction.areas",
        "conditionElement1Fixed": "",
        "conditionAttribute1": "count",
        "conditionTest": ">=",
        "conditionElement2": "",
        "conditionElement2Fixed": "9",
        "conditionAttribute2": "",
        "groupName": "areaCenterGroup"
      }
    ],
    "cadres": [
      {
        "name": "categorieCadre",
        "backgroundColor": "",
        "color": "",
        "DynamicBackgroundColor": "category.categoryColor",
        "DynamicColor": "",
        "style": "",
        "position": "absolute",
        "maxWidth": "333px",
        "maxHeight": "227px",
        "width": "333px",
        "height": "147px",
        "x": "48px",
        "y": "261px",
        "z": "",
        "margin": "",
        "padding": "",
        "border": "",
        "display": "inline-block",
        "verticalAlign": "",
        "hidden": false
      },
      {
        "name": "fonctionCadre",
        "backgroundColor": "",
        "color": "",
        "DynamicBackgroundColor": "fonction.fonctionColor",
        "DynamicColor": "",
        "style": "",
        "position": "absolute",
        "maxWidth": "",
        "maxHeight": "",
        "width": "",
        "height": "",
        "x": "",
        "y": "",
        "z": "",
        "margin": "",
        "padding": "",
        "border": "",
        "display": "inline-block",
        "verticalAlign": "",
        "hidden": false
      }
    ],
    "codes": [
      {
        "name": "accreditationQrCode",
        "sourceType": "attribute",
        "codeValuepath": "code.codeValue",
        "codeTypePath": "code.codeType.codeTypeValue",
        "type": "text",
        "format": "",
        "style": "",
        "position": "absolute",
        "maxWidth": "100px",
        "maxHeight": "100px",
        "width": "100px",
        "height": "100px",
        "x": "273px",
        "y": "266px",
        "z": "",
        "margin": "",
        "padding": "",
        "backgroundColor": "",
        "color": "",
        "DynamicBackgroundColor": "",
        "DynamicColor": "",
        "textAlign": "",
        "fontFamily": "",
        "fontStyle": "",
        "fontSize": "",
        "fontWeight": "",
        "border": "",
        "display": "inline-block",
        "whiteSpace": "",
        "toUpperCase": false,
        "verticalAlign": "",
        "hidden": false
      }
    ]
  }
}